ZuheYuyanZhiYishu/README.md
ZuheYuyanZhiYishu/__init__.py
ZuheYuyanZhiYishu/__main__.py
ZuheYuyanZhiYishu/file.epub
ZuheYuyanZhiYishu/index.html
ZuheYuyanZhiYishu/css/__init__.py
ZuheYuyanZhiYishu/css/annotations.css
ZuheYuyanZhiYishu/css/main.css
ZuheYuyanZhiYishu/css/normalize.css
ZuheYuyanZhiYishu/css/popup.css
ZuheYuyanZhiYishu/font/__init__.py
ZuheYuyanZhiYishu/font/fontello.eot
ZuheYuyanZhiYishu/font/fontello.svg
ZuheYuyanZhiYishu/font/fontello.ttf
ZuheYuyanZhiYishu/font/fontello.woff
ZuheYuyanZhiYishu/img/__init__.py
ZuheYuyanZhiYishu/img/annotator-glyph-sprite.png
ZuheYuyanZhiYishu/img/annotator-icon-sprite.png
ZuheYuyanZhiYishu/img/apple-touch-icon.png
ZuheYuyanZhiYishu/img/cancelfullscreen.png
ZuheYuyanZhiYishu/img/close.png
ZuheYuyanZhiYishu/img/fullscreen.png
ZuheYuyanZhiYishu/img/loader.gif
ZuheYuyanZhiYishu/img/menu-icon.png
ZuheYuyanZhiYishu/img/save.png
ZuheYuyanZhiYishu/img/saved.png
ZuheYuyanZhiYishu/img/settings-s.png
ZuheYuyanZhiYishu/img/settings.png
ZuheYuyanZhiYishu/img/star.png
ZuheYuyanZhiYishu/js/__init__.py
ZuheYuyanZhiYishu/js/epub.js
ZuheYuyanZhiYishu/js/epub.min.js
ZuheYuyanZhiYishu/js/epub.min.map
ZuheYuyanZhiYishu/js/hooks.min.js
ZuheYuyanZhiYishu/js/hooks.min.map
ZuheYuyanZhiYishu/js/reader.js
ZuheYuyanZhiYishu/js/reader.js.map
ZuheYuyanZhiYishu/js/reader.min.js
ZuheYuyanZhiYishu/js/reader.min.map
ZuheYuyanZhiYishu/js/hooks/__init__.py
ZuheYuyanZhiYishu/js/hooks/extensions/__init__.py
ZuheYuyanZhiYishu/js/hooks/extensions/highlight.js
ZuheYuyanZhiYishu/js/libs/__init__.py
ZuheYuyanZhiYishu/js/libs/jquery.min.js
ZuheYuyanZhiYishu/js/libs/localforage.min.js
ZuheYuyanZhiYishu/js/libs/screenfull.js
ZuheYuyanZhiYishu/js/libs/screenfull.min.js
ZuheYuyanZhiYishu/js/libs/zip.min.js
ZuheYuyanZhiYishu/js/plugins/__init__.py
ZuheYuyanZhiYishu/js/plugins/hypothesis.js
ZuheYuyanZhiYishu/js/plugins/search.js
zuhe_yuyan_zhi_yishu-2024.3.2.0.dist-info/METADATA
zuhe_yuyan_zhi_yishu-2024.3.2.0.dist-info/WHEEL
zuhe_yuyan_zhi_yishu-2024.3.2.0.dist-info/entry_points.txt
zuhe_yuyan_zhi_yishu-2024.3.2.0.dist-info/top_level.txt
zuhe_yuyan_zhi_yishu-2024.3.2.0.dist-info/RECORD
